{"BBLE":"3073350002","BORO":"3.00","BLOCK":"7335.00","LOT":"2.00","SECVOL":"2202.00","DISTRICT":"21","NEW_FV_L":"177000.00","NEW_FV_T":"418000.00","TXCL":"1","O_TXCL":"1","BLDGCL":"B1","OWNER":"LIU, BILLY YUAN BIAO","HNUM_LO":"000000002932","HNUM_HI":"000000002932","STR_NAME":"AVENUE T","ZIP":"11229.00","TOT_UNIT":"2.00","RES_UNIT":"2.00","LFRT_DEC":"0021.00","LDEP_DEC":"0100.00","BFRT_DEC":"0021.00","BDEP_DEC":"0045.00","STORY":"001.00","BLDGS":"1.00","CORNER":"","LND_AREA":"2100.00","GR_SQFT":"1701.00","ZONING":"R4","YRB":"1945.00","CP_BORO":"3.00","CP_DIST":"15.00","APTNO":""}