{"BBLE":"4082240063","BORO":"4.00","BLOCK":"8224.00","LOT":"63.00","SECVOL":"3604.00","DISTRICT":"13","NEW_FV_L":"315000.00","NEW_FV_T":"769000.00","TXCL":"1","O_TXCL":"1","BLDGCL":"A0","OWNER":"XIE XIANG","HNUM_LO":"000000248-08","HNUM_HI":"000000248-08","STR_NAME":"THORNHILL AVENUE","ZIP":"11362.00","TOT_UNIT":"1.00","RES_UNIT":"1.00","LFRT_DEC":"0054.00","LDEP_DEC":"0106.00","BFRT_DEC":"0035.00","BDEP_DEC":"0028.00","STORY":"001.50","BLDGS":"1.00","CORNER":"","LND_AREA":"5562.00","GR_SQFT":"2205.00","ZONING":"R2A","YRB":"1945.00","CP_BORO":"4.00","CP_DIST":"11.00","APTNO":""}