{"BBLE":"4051480059","BORO":"4.00","BLOCK":"5148.00","LOT":"59.00","SECVOL":"2505.00","DISTRICT":"11","NEW_FV_L":"262000.00","NEW_FV_T":"583000.00","TXCL":"1","O_TXCL":"1","BLDGCL":"B2","OWNER":"LIU, YAO XING","HNUM_LO":"000000137-29","HNUM_HI":"000000137-29","STR_NAME":"JUNIPER AVENUE","ZIP":"11355.00","TOT_UNIT":"2.00","RES_UNIT":"2.00","LFRT_DEC":"0024.00","LDEP_DEC":"0100.00","BFRT_DEC":"0016.00","BDEP_DEC":"0032.00","STORY":"002.75","BLDGS":"1.00","CORNER":"","LND_AREA":"2400.00","GR_SQFT":"1696.00","ZONING":"R3-2","YRB":"1930.00","CP_BORO":"4.00","CP_DIST":"7.00","APTNO":""}