{"BBLE":"5037030015","BORO":"5.00","BLOCK":"3703.00","LOT":"15.00","SECVOL":"1701.00","DISTRICT":"04","NEW_FV_L":"90000.00","NEW_FV_T":"260000.00","TXCL":"1","O_TXCL":"1","BLDGCL":"A5","OWNER":"DANIEL J PAPA","HNUM_LO":"000000000318","HNUM_HI":"000000000318","STR_NAME":"SANILAC STREET","ZIP":"10306.00","TOT_UNIT":"1.00","RES_UNIT":"1.00","LFRT_DEC":"0021.00","LDEP_DEC":"0100.00","BFRT_DEC":"0015.00","BDEP_DEC":"0040.00","STORY":"002.00","BLDGS":"1.00","CORNER":"","LND_AREA":"2100.00","GR_SQFT":"1200.00","ZONING":"R3-1","YRB":"1960.00","CP_BORO":"5.00","CP_DIST":"2.00","APTNO":""}