{"BBLE":"4092210053","BORO":"4.00","BLOCK":"9221.00","LOT":"53.00","SECVOL":"4001.00","DISTRICT":"15","NEW_FV_L":"313000.00","NEW_FV_T":"596000.00","TXCL":"1","O_TXCL":"1","BLDGCL":"B3","OWNER":"NATHOO HILTON H","HNUM_LO":"000000085-74","HNUM_HI":"000000085-74","STR_NAME":"114 STREET","ZIP":"11418.00","TOT_UNIT":"2.00","RES_UNIT":"2.00","LFRT_DEC":"0050.00","LDEP_DEC":"0100.00","BFRT_DEC":"0022.00","BDEP_DEC":"0030.00","STORY":"002.50","BLDGS":"1.00","CORNER":"","LND_AREA":"5000.00","GR_SQFT":"2566.00","ZONING":"R3X","YRB":"1920.00","CP_BORO":"4.00","CP_DIST":"9.00","APTNO":""}