{"BBLE":"3055970002","BORO":"3.00","BLOCK":"5597.00","LOT":"2.00","SECVOL":"1705.00","DISTRICT":"17","NEW_FV_L":"220000.00","NEW_FV_T":"404000.00","TXCL":"1","O_TXCL":"1","BLDGCL":"S1","OWNER":"WEISS  LEWIS","HNUM_LO":"000000004221","HNUM_HI":"000000004221","STR_NAME":"FT HAMILTON PARKWAY","ZIP":"11219.00","TOT_UNIT":"2.00","RES_UNIT":"1.00","LFRT_DEC":"0020.33","LDEP_DEC":"0092.67","BFRT_DEC":"0020.00","BDEP_DEC":"0060.00","STORY":"002.00","BLDGS":"1.00","CORNER":"","LND_AREA":"2325.00","GR_SQFT":"2400.00","ZONING":"R6","YRB":"1930.00","CP_BORO":"3.00","CP_DIST":"12.00","APTNO":""}