{"BBLE":"4126290019","BORO":"4.00","BLOCK":"12629.00","LOT":"19.00","SECVOL":"5401.00","DISTRICT":"18","NEW_FV_L":"220000.00","NEW_FV_T":"328000.00","TXCL":"1","O_TXCL":"1","BLDGCL":"A2","OWNER":"JEAN ROBERT DORSIN","HNUM_LO":"000000118-26","HNUM_HI":"000000118-26","STR_NAME":"201 STREET","ZIP":"11412.00","TOT_UNIT":"1.00","RES_UNIT":"1.00","LFRT_DEC":"0040.00","LDEP_DEC":"0100.00","BFRT_DEC":"0035.00","BDEP_DEC":"0025.00","STORY":"001.50","BLDGS":"1.00","CORNER":"","LND_AREA":"4000.00","GR_SQFT":"1094.00","ZONING":"R4A","YRB":"1955.00","CP_BORO":"4.00","CP_DIST":"12.00","APTNO":""}