{"BBLE":"3012780037","BORO":"3.00","BLOCK":"1278.00","LOT":"37.00","SECVOL":"503.00","DISTRICT":"05","NEW_FV_L":"243000.00","NEW_FV_T":"445000.00","TXCL":"1","O_TXCL":"1","BLDGCL":"S1","OWNER":"MACHNE ISRAEL INC","HNUM_LO":"000000000312","HNUM_HI":"000000000312","STR_NAME":"KINGSTON AVENUE","ZIP":"11213.00","TOT_UNIT":"2.00","RES_UNIT":"1.00","LFRT_DEC":"0020.00","LDEP_DEC":"0070.00","BFRT_DEC":"0020.00","BDEP_DEC":"0057.00","STORY":"002.00","BLDGS":"1.00","CORNER":"","LND_AREA":"1400.00","GR_SQFT":"2280.00","ZONING":"R4","YRB":"1925.00","CP_BORO":"3.00","CP_DIST":"9.00","APTNO":""}