{"BBLE":"4016010055","BORO":"4.00","BLOCK":"1601.00","LOT":"55.00","SECVOL":"906.00","DISTRICT":"05","NEW_FV_L":"386000.00","NEW_FV_T":"581000.00","TXCL":"1","O_TXCL":"1","BLDGCL":"B2","OWNER":"JAMES APOSTOLATOS","HNUM_LO":"000000094-51","HNUM_HI":"000000094-51","STR_NAME":"44 AVENUE","ZIP":"11373.00","TOT_UNIT":"2.00","RES_UNIT":"2.00","LFRT_DEC":"0025.00","LDEP_DEC":"0100.00","BFRT_DEC":"0020.00","BDEP_DEC":"0045.00","STORY":"002.50","BLDGS":"1.00","CORNER":"","LND_AREA":"2500.00","GR_SQFT":"2410.00","ZONING":"R5","YRB":"1910.00","CP_BORO":"4.00","CP_DIST":"4.00","APTNO":""}