{"BBLE":"3077240056","BORO":"3.00","BLOCK":"7724.00","LOT":"56.00","SECVOL":"2306.00","DISTRICT":"21","NEW_FV_L":"236000.00","NEW_FV_T":"304000.00","TXCL":"1","O_TXCL":"1","BLDGCL":"A1","OWNER":"PLOWDEN HORACE KEITH","HNUM_LO":"000000001628","HNUM_HI":"000000001628","STR_NAME":"ALBANY AVENUE","ZIP":"11210.00","TOT_UNIT":"1.00","RES_UNIT":"1.00","LFRT_DEC":"0024.00","LDEP_DEC":"0100.00","BFRT_DEC":"0014.00","BDEP_DEC":"0036.00","STORY":"002.00","BLDGS":"1.00","CORNER":"","LND_AREA":"2400.00","GR_SQFT":"1120.00","ZONING":"R4","YRB":"1920.00","CP_BORO":"3.00","CP_DIST":"17.00","APTNO":""}