{"BBLE":"3053170028","BORO":"3.00","BLOCK":"5317.00","LOT":"28.00","SECVOL":"1607.00","DISTRICT":"16","NEW_FV_L":"421000.00","NEW_FV_T":"710000.00","TXCL":"1","O_TXCL":"1","BLDGCL":"A1","OWNER":"SCLAFANI, GERARD","HNUM_LO":"000000000301","HNUM_HI":"000000000301","STR_NAME":"CATON AVENUE","ZIP":"11218.00","TOT_UNIT":"1.00","RES_UNIT":"1.00","LFRT_DEC":"0020.00","LDEP_DEC":"0100.00","BFRT_DEC":"0020.00","BDEP_DEC":"0036.00","STORY":"002.00","BLDGS":"1.00","CORNER":"NE","LND_AREA":"2000.00","GR_SQFT":"2165.00","ZONING":"R5","YRB":"1915.00","CP_BORO":"3.00","CP_DIST":"7.00","APTNO":""}