{"BBLE":"3056460065","BORO":"3.00","BLOCK":"5646.00","LOT":"65.00","SECVOL":"1706.00","DISTRICT":"18","NEW_FV_L":"486000.00","NEW_FV_T":"877000.00","TXCL":"1","O_TXCL":"1","BLDGCL":"B1","OWNER":"YISROEL M. STUHL, AS","HNUM_LO":"000000001053","HNUM_HI":"000000001053","STR_NAME":"51 STREET","ZIP":"11219.00","TOT_UNIT":"2.00","RES_UNIT":"2.00","LFRT_DEC":"0028.00","LDEP_DEC":"0100.17","BFRT_DEC":"0020.00","BDEP_DEC":"0067.00","STORY":"002.00","BLDGS":"1.00","CORNER":"","LND_AREA":"2805.00","GR_SQFT":"2680.00","ZONING":"R6","YRB":"1920.00","CP_BORO":"3.00","CP_DIST":"12.00","APTNO":""}