{"BBLE":"2023140071","BORO":"2.00","BLOCK":"2314.00","LOT":"71.00","SECVOL":"902.00","DISTRICT":"01","NEW_FV_L":"250000.00","NEW_FV_T":"327000.00","TXCL":"1","O_TXCL":"1","BLDGCL":"A5","OWNER":"IOTHA JOSEPH","HNUM_LO":"000000000291","HNUM_HI":"000000000291","STR_NAME":"ALEXANDER AVENUE","ZIP":"10454.00","TOT_UNIT":"1.00","RES_UNIT":"1.00","LFRT_DEC":"0016.58","LDEP_DEC":"0070.42","BFRT_DEC":"0016.58","BDEP_DEC":"0042.00","STORY":"003.00","BLDGS":"1.00","CORNER":"","LND_AREA":"1127.00","GR_SQFT":"2724.00","ZONING":"R6","YRB":"1899.00","CP_BORO":"2.00","CP_DIST":"1.00","APTNO":""}