{"BBLE":"4159030018","BORO":"4.00","BLOCK":"15903.00","LOT":"18.00","SECVOL":"6102.00","DISTRICT":"20","NEW_FV_L":"122816.00","NEW_FV_T":"343000.00","TXCL":"1","O_TXCL":"1","BLDGCL":"B1","OWNER":"JAMES, ROSELINE","HNUM_LO":"000000000196","HNUM_HI":"000000000196","STR_NAME":"BEACH 61 STREET","ZIP":"11692.00","TOT_UNIT":"2.00","RES_UNIT":"2.00","LFRT_DEC":"0038.51","LDEP_DEC":"0096.16","BFRT_DEC":"0033.00","BDEP_DEC":"0044.00","STORY":"002.00","BLDGS":"1.00","CORNER":"NW","LND_AREA":"4392.00","GR_SQFT":"2052.00","ZONING":"R6","YRB":"2000.00","CP_BORO":"4.00","CP_DIST":"14.00","APTNO":""}