{"BBLE":"4087870001","BORO":"4.00","BLOCK":"8787.00","LOT":"1.00","SECVOL":"3805.00","DISTRICT":"14","NEW_FV_L":"307000.00","NEW_FV_T":"554000.00","TXCL":"1","O_TXCL":"1","BLDGCL":"B2","OWNER":"SEKHON, JATINDER SING","HNUM_LO":"000000257-02","HNUM_HI":"000000257-02","STR_NAME":"HILLSIDE AVENUE","ZIP":"11004.00","TOT_UNIT":"2.00","RES_UNIT":"2.00","LFRT_DEC":"0022.00","LDEP_DEC":"0100.00","BFRT_DEC":"0021.00","BDEP_DEC":"0036.83","STORY":"002.00","BLDGS":"1.00","CORNER":"CR","LND_AREA":"2300.00","GR_SQFT":"1584.00","ZONING":"R2","YRB":"1970.00","CP_BORO":"4.00","CP_DIST":"13.00","APTNO":""}