{"BBLE":"3007370072","BORO":"3.00","BLOCK":"737.00","LOT":"72.00","SECVOL":"304.00","DISTRICT":"03","NEW_FV_L":"211000.00","NEW_FV_T":"595000.00","TXCL":"1","O_TXCL":"1","BLDGCL":"B9","OWNER":"ROBLES, JUAN JOSE","HNUM_LO":"000000000313","HNUM_HI":"000000000313","STR_NAME":"45 STREET","ZIP":"11220.00","TOT_UNIT":"2.00","RES_UNIT":"2.00","LFRT_DEC":"0020.00","LDEP_DEC":"0100.17","BFRT_DEC":"0020.00","BDEP_DEC":"0050.00","STORY":"002.00","BLDGS":"1.00","CORNER":"CR","LND_AREA":"2003.00","GR_SQFT":"2820.00","ZONING":"R6B","YRB":"1899.00","CP_BORO":"3.00","CP_DIST":"7.00","APTNO":""}