{"BBLE":"2031130037","BORO":"2.00","BLOCK":"3113.00","LOT":"37.00","SECVOL":"1108.00","DISTRICT":"10","NEW_FV_L":"278000.00","NEW_FV_T":"376000.00","TXCL":"1","O_TXCL":"1","BLDGCL":"C0","OWNER":"LUMAJ, DAVID","HNUM_LO":"000000002297","HNUM_HI":"000000002297","STR_NAME":"SOUTHERN BOULEVARD","ZIP":"10460.00","TOT_UNIT":"3.00","RES_UNIT":"3.00","LFRT_DEC":"0025.30","LDEP_DEC":"0109.28","BFRT_DEC":"0021.00","BDEP_DEC":"0069.00","STORY":"002.00","BLDGS":"1.00","CORNER":"","LND_AREA":"2780.00","GR_SQFT":"3042.00","ZONING":"R7-1","YRB":"1925.00","CP_BORO":"2.00","CP_DIST":"6.00","APTNO":""}