{"BBLE":"3073610041","BORO":"3.00","BLOCK":"7361.00","LOT":"41.00","SECVOL":"2203.00","DISTRICT":"20","NEW_FV_L":"199083.00","NEW_FV_T":"499000.00","TXCL":"1","O_TXCL":"1","BLDGCL":"B1","OWNER":"YELANCHIK, YELANCHIK","HNUM_LO":"000000002142","HNUM_HI":"000000002142","STR_NAME":"EAST 29 STREET","ZIP":"11229.00","TOT_UNIT":"2.00","RES_UNIT":"2.00","LFRT_DEC":"0018.00","LDEP_DEC":"0100.00","BFRT_DEC":"0018.00","BDEP_DEC":"0037.00","STORY":"002.00","BLDGS":"1.00","CORNER":"","LND_AREA":"1800.00","GR_SQFT":"2022.00","ZONING":"R4","YRB":"1940.00","CP_BORO":"3.00","CP_DIST":"15.00","APTNO":""}