{"BBLE":"5006700037","BORO":"5.00","BLOCK":"670.00","LOT":"37.00","SECVOL":"304.00","DISTRICT":"02","NEW_FV_L":"239000.00","NEW_FV_T":"425000.00","TXCL":"1","O_TXCL":"1","BLDGCL":"B9","OWNER":"JUAN ARANGO","HNUM_LO":"000000000108","HNUM_HI":"000000000108","STR_NAME":"LOGAN AVENUE","ZIP":"10301.00","TOT_UNIT":"2.00","RES_UNIT":"2.00","LFRT_DEC":"0030.00","LDEP_DEC":"0100.00","BFRT_DEC":"0022.00","BDEP_DEC":"0051.00","STORY":"002.00","BLDGS":"1.00","CORNER":"","LND_AREA":"3000.00","GR_SQFT":"1828.00","ZONING":"R3-1","YRB":"1975.00","CP_BORO":"5.00","CP_DIST":"1.00","APTNO":""}