{"BBLE":"4028410041","BORO":"4.00","BLOCK":"2841.00","LOT":"41.00","SECVOL":"1503.00","DISTRICT":"08","NEW_FV_L":"273000.00","NEW_FV_T":"523000.00","TXCL":"1","O_TXCL":"1","BLDGCL":"A5","OWNER":"DOREEN ZAWADZKI","HNUM_LO":"000000060-74","HNUM_HI":"000000060-74","STR_NAME":"71 STREET","ZIP":"11378.00","TOT_UNIT":"1.00","RES_UNIT":"1.00","LFRT_DEC":"0016.00","LDEP_DEC":"0100.00","BFRT_DEC":"0016.00","BDEP_DEC":"0030.00","STORY":"002.00","BLDGS":"1.00","CORNER":"","LND_AREA":"1600.00","GR_SQFT":"1200.00","ZONING":"R4","YRB":"1940.00","CP_BORO":"4.00","CP_DIST":"5.00","APTNO":""}